setup.py
mhashlib/__init__.py
mhashlib/api.py
mhashlib/base.py
py_mhash.egg-info/PKG-INFO
py_mhash.egg-info/SOURCES.txt
py_mhash.egg-info/dependency_links.txt
py_mhash.egg-info/not-zip-safe
py_mhash.egg-info/top_level.txt