Metadata-Version: 1.1
Name: py-mhash
Version: 1.2
Summary: Mhash ctypes bindings for Python.
Home-page: https://github.com/niwibe/py-mhash
Author: Andrei Antoukh
Author-email: niwi@niwi.be
License: UNKNOWN
Platform: UNKNOWN
Classifier: Development Status :: 5 - Production/Stable
Classifier: Environment :: Web Environment
Classifier: License :: OSI Approved :: BSD License
Classifier: Intended Audience :: Developers
Classifier: Programming Language :: Python
Classifier: Programming Language :: Python :: 2
Classifier: Programming Language :: Python :: 2.7
Classifier: Programming Language :: Python :: 3
Classifier: Programming Language :: Python :: 3.2
Classifier: Programming Language :: Python :: 3.3
Classifier: Topic :: Software Development :: Libraries
Classifier: Topic :: Utilities
